odp_sdk/__init__.py
odp_sdk/auth.py
odp_sdk/client.py
odp_sdk/dto/__init__.py
odp_sdk/dto/file_dto.py
odp_sdk/dto/resource_dto.py
odp_sdk/dto/table_spec.py
odp_sdk/dto/tabular_store.py
odp_sdk/exc.py
odp_sdk/http_client.py
odp_sdk/raw_storage_client.py
odp_sdk/resource_client.py
odp_sdk/tabular_storage_client.py
odp_sdk/utils/__init__.py
odp_sdk/utils/json.py
odp_sdk/utils/ndjson.py
odp_sdk_python-0.4.1.dist-info/LICENSE
odp_sdk_python-0.4.1.dist-info/METADATA
odp_sdk_python-0.4.1.dist-info/WHEEL
odp_sdk_python-0.4.1.dist-info/RECORD
