Metadata-Version: 2.1
Name: odp-sdk-python
Version: 0.4.1
Summary: ODP Python SDK
License: MIT
Author: Thomas Li Fredriksen
Author-email: thomas.fredriksen@oceandata.earth
Requires-Python: >=3.10,<4.0
Classifier: License :: OSI Approved :: MIT License
Classifier: Programming Language :: Python :: 3
Classifier: Programming Language :: Python :: 3.10
Classifier: Programming Language :: Python :: 3.11
Classifier: Programming Language :: Python :: 3.12
Provides-Extra: pandas
Requires-Dist: cryptography (>=41.0.5,<42.0.0)
Requires-Dist: msal (>=1.24.1,<2.0.0)
Requires-Dist: msal-extensions (>=1.1.0,<2.0.0)
Requires-Dist: pandas (>=2.1.4,<3.0.0) ; extra == "pandas"
Requires-Dist: pydantic (>=2.4.2,<3.0.0)
Requires-Dist: pyjwt (>=2.8.0,<3.0.0)
